{"atlas": {"distanceRange": 1, "width": 1186, "height": 16, "size": 12, "type": "hardmask", "yOrigin": "bottom"}, "glyphs": [{"advance": 0.5833333333333334, "unicode": 32}, {"advance": 0.75, "unicode": 65, "atlasBounds": {"top": 16, "left": 0, "bottom": 0, "right": 8}, "planeBounds": {"top": 1.0, "left": 0, "bottom": -0.3333333333333333, "right": 0.6666666666666666}}, {"advance": 0.6666666666666666, "unicode": 66, "atlasBounds": {"top": 16, "left": 9, "bottom": 0, "right": 16}, "planeBounds": {"top": 1.0, "left": 0, "bottom": -0.3333333333333333, "right": 0.5833333333333334}}, {"advance": 0.5833333333333334, "unicode": 67, "atlasBounds": {"top": 16, "left": 17, "bottom": 0, "right": 23}, "planeBounds": {"top": 1.0, "left": 0, "bottom": -0.3333333333333333, "right": 0.5}}, {"advance": 0.6666666666666666, "unicode": 68, "atlasBounds": {"top": 16, "left": 24, "bottom": 0, "right": 31}, "planeBounds": {"top": 1.0, "left": 0, "bottom": -0.3333333333333333, "right": 0.5833333333333334}}, {"advance": 0.6666666666666666, "unicode": 69, "atlasBounds": {"top": 16, "left": 32, "bottom": 0, "right": 39}, "planeBounds": {"top": 1.0, "left": 0, "bottom": -0.3333333333333333, "right": 0.5833333333333334}}, {"advance": 0.6666666666666666, "unicode": 70, "atlasBounds": {"top": 16, "left": 40, "bottom": 0, "right": 47}, "planeBounds": {"top": 1.0, "left": 0, "bottom": -0.3333333333333333, "right": 0.5833333333333334}}, {"advance": 0.5833333333333334, "unicode": 71, "atlasBounds": {"top": 16, "left": 48, "bottom": 0, "right": 54}, "planeBounds": {"top": 1.0, "left": 0, "bottom": -0.3333333333333333, "right": 0.5}}, {"advance": 0.75, "unicode": 72, "atlasBounds": {"top": 16, "left": 55, "bottom": 0, "right": 63}, "planeBounds": {"top": 1.0, "left": 0, "bottom": -0.3333333333333333, "right": 0.6666666666666666}}, {"advance": 0.4166666666666667, "unicode": 73, "atlasBounds": {"top": 16, "left": 64, "bottom": 0, "right": 68}, "planeBounds": {"top": 1.0, "left": 0, "bottom": -0.3333333333333333, "right": 0.3333333333333333}}, {"advance": 0.5833333333333334, "unicode": 74, "atlasBounds": {"top": 16, "left": 69, "bottom": 0, "right": 75}, "planeBounds": {"top": 1.0, "left": 0, "bottom": -0.3333333333333333, "right": 0.5}}, {"advance": 0.75, "unicode": 75, "atlasBounds": {"top": 16, "left": 76, "bottom": 0, "right": 84}, "planeBounds": {"top": 1.0, "left": 0, "bottom": -0.3333333333333333, "right": 0.6666666666666666}}, {"advance": 0.6666666666666666, "unicode": 76, "atlasBounds": {"top": 16, "left": 85, "bottom": 0, "right": 92}, "planeBounds": {"top": 1.0, "left": 0, "bottom": -0.3333333333333333, "right": 0.5833333333333334}}, {"advance": 0.8333333333333334, "unicode": 77, "atlasBounds": {"top": 16, "left": 93, "bottom": 0, "right": 102}, "planeBounds": {"top": 1.0, "left": 0, "bottom": -0.3333333333333333, "right": 0.75}}, {"advance": 0.8333333333333334, "unicode": 78, "atlasBounds": {"top": 16, "left": 103, "bottom": 0, "right": 112}, "planeBounds": {"top": 1.0, "left": 0, "bottom": -0.3333333333333333, "right": 0.75}}, {"advance": 0.6666666666666666, "unicode": 79, "atlasBounds": {"top": 16, "left": 113, "bottom": 0, "right": 120}, "planeBounds": {"top": 1.0, "left": 0, "bottom": -0.3333333333333333, "right": 0.5833333333333334}}, {"advance": 0.6666666666666666, "unicode": 80, "atlasBounds": {"top": 16, "left": 121, "bottom": 0, "right": 128}, "planeBounds": {"top": 1.0, "left": 0, "bottom": -0.3333333333333333, "right": 0.5833333333333334}}, {"advance": 0.6666666666666666, "unicode": 81, "atlasBounds": {"top": 16, "left": 129, "bottom": 0, "right": 136}, "planeBounds": {"top": 1.0, "left": 0, "bottom": -0.3333333333333333, "right": 0.5833333333333334}}, {"advance": 0.75, "unicode": 82, "atlasBounds": {"top": 16, "left": 137, "bottom": 0, "right": 145}, "planeBounds": {"top": 1.0, "left": 0, "bottom": -0.3333333333333333, "right": 0.6666666666666666}}, {"advance": 0.5833333333333334, "unicode": 83, "atlasBounds": {"top": 16, "left": 146, "bottom": 0, "right": 152}, "planeBounds": {"top": 1.0, "left": 0, "bottom": -0.3333333333333333, "right": 0.5}}, {"advance": 0.75, "unicode": 84, "atlasBounds": {"top": 16, "left": 153, "bottom": 0, "right": 161}, "planeBounds": {"top": 1.0, "left": 0, "bottom": -0.3333333333333333, "right": 0.6666666666666666}}, {"advance": 0.6666666666666666, "unicode": 85, "atlasBounds": {"top": 16, "left": 162, "bottom": 0, "right": 169}, "planeBounds": {"top": 1.0, "left": 0, "bottom": -0.3333333333333333, "right": 0.5833333333333334}}, {"advance": 0.5833333333333334, "unicode": 86, "atlasBounds": {"top": 16, "left": 170, "bottom": 0, "right": 176}, "planeBounds": {"top": 1.0, "left": 0, "bottom": -0.3333333333333333, "right": 0.5}}, {"advance": 0.9166666666666666, "unicode": 87, "atlasBounds": {"top": 16, "left": 177, "bottom": 0, "right": 187}, "planeBounds": {"top": 1.0, "left": 0, "bottom": -0.3333333333333333, "right": 0.8333333333333334}}, {"advance": 0.5833333333333334, "unicode": 88, "atlasBounds": {"top": 16, "left": 188, "bottom": 0, "right": 194}, "planeBounds": {"top": 1.0, "left": 0, "bottom": -0.3333333333333333, "right": 0.5}}, {"advance": 0.75, "unicode": 89, "atlasBounds": {"top": 16, "left": 195, "bottom": 0, "right": 203}, "planeBounds": {"top": 1.0, "left": 0, "bottom": -0.3333333333333333, "right": 0.6666666666666666}}, {"advance": 0.5833333333333334, "unicode": 90, "atlasBounds": {"top": 16, "left": 204, "bottom": 0, "right": 210}, "planeBounds": {"top": 1.0, "left": 0, "bottom": -0.3333333333333333, "right": 0.5}}, {"advance": 0.5833333333333334, "unicode": 97, "atlasBounds": {"top": 16, "left": 211, "bottom": 0, "right": 217}, "planeBounds": {"top": 1.0, "left": 0, "bottom": -0.3333333333333333, "right": 0.5}}, {"advance": 0.6666666666666666, "unicode": 98, "atlasBounds": {"top": 16, "left": 218, "bottom": 0, "right": 225}, "planeBounds": {"top": 1.0, "left": 0, "bottom": -0.3333333333333333, "right": 0.5833333333333334}}, {"advance": 0.5833333333333334, "unicode": 99, "atlasBounds": {"top": 16, "left": 226, "bottom": 0, "right": 232}, "planeBounds": {"top": 1.0, "left": 0, "bottom": -0.3333333333333333, "right": 0.5}}, {"advance": 0.6666666666666666, "unicode": 100, "atlasBounds": {"top": 16, "left": 233, "bottom": 0, "right": 240}, "planeBounds": {"top": 1.0, "left": 0, "bottom": -0.3333333333333333, "right": 0.5833333333333334}}, {"advance": 0.5833333333333334, "unicode": 101, "atlasBounds": {"top": 16, "left": 241, "bottom": 0, "right": 247}, "planeBounds": {"top": 1.0, "left": 0, "bottom": -0.3333333333333333, "right": 0.5}}, {"advance": 0.4166666666666667, "unicode": 102, "atlasBounds": {"top": 16, "left": 248, "bottom": 0, "right": 252}, "planeBounds": {"top": 1.0, "left": 0, "bottom": -0.3333333333333333, "right": 0.3333333333333333}}, {"advance": 0.5833333333333334, "unicode": 103, "atlasBounds": {"top": 16, "left": 253, "bottom": 0, "right": 259}, "planeBounds": {"top": 1.0, "left": 0, "bottom": -0.3333333333333333, "right": 0.5}}, {"advance": 0.6666666666666666, "unicode": 104, "atlasBounds": {"top": 16, "left": 260, "bottom": 0, "right": 267}, "planeBounds": {"top": 1.0, "left": 0, "bottom": -0.3333333333333333, "right": 0.5833333333333334}}, {"advance": 0.4166666666666667, "unicode": 105, "atlasBounds": {"top": 16, "left": 268, "bottom": 0, "right": 272}, "planeBounds": {"top": 1.0, "left": 0, "bottom": -0.3333333333333333, "right": 0.3333333333333333}}, {"advance": 0.5, "unicode": 106, "atlasBounds": {"top": 16, "left": 273, "bottom": 0, "right": 278}, "planeBounds": {"top": 1.0, "left": 0, "bottom": -0.3333333333333333, "right": 0.4166666666666667}}, {"advance": 0.6666666666666666, "unicode": 107, "atlasBounds": {"top": 16, "left": 279, "bottom": 0, "right": 286}, "planeBounds": {"top": 1.0, "left": 0, "bottom": -0.3333333333333333, "right": 0.5833333333333334}}, {"advance": 0.3333333333333333, "unicode": 108, "atlasBounds": {"top": 16, "left": 287, "bottom": 0, "right": 290}, "planeBounds": {"top": 1.0, "left": 0, "bottom": -0.3333333333333333, "right": 0.25}}, {"advance": 0.6666666666666666, "unicode": 109, "atlasBounds": {"top": 16, "left": 291, "bottom": 0, "right": 298}, "planeBounds": {"top": 1.0, "left": 0, "bottom": -0.3333333333333333, "right": 0.5833333333333334}}, {"advance": 0.5833333333333334, "unicode": 110, "atlasBounds": {"top": 16, "left": 299, "bottom": 0, "right": 305}, "planeBounds": {"top": 1.0, "left": 0, "bottom": -0.3333333333333333, "right": 0.5}}, {"advance": 0.5833333333333334, "unicode": 111, "atlasBounds": {"top": 16, "left": 306, "bottom": 0, "right": 312}, "planeBounds": {"top": 1.0, "left": 0, "bottom": -0.3333333333333333, "right": 0.5}}, {"advance": 0.6666666666666666, "unicode": 112, "atlasBounds": {"top": 16, "left": 313, "bottom": 0, "right": 320}, "planeBounds": {"top": 1.0, "left": 0, "bottom": -0.3333333333333333, "right": 0.5833333333333334}}, {"advance": 0.6666666666666666, "unicode": 113, "atlasBounds": {"top": 16, "left": 321, "bottom": 0, "right": 328}, "planeBounds": {"top": 1.0, "left": 0, "bottom": -0.3333333333333333, "right": 0.5833333333333334}}, {"advance": 0.5833333333333334, "unicode": 114, "atlasBounds": {"top": 16, "left": 329, "bottom": 0, "right": 335}, "planeBounds": {"top": 1.0, "left": 0, "bottom": -0.3333333333333333, "right": 0.5}}, {"advance": 0.5, "unicode": 115, "atlasBounds": {"top": 16, "left": 336, "bottom": 0, "right": 341}, "planeBounds": {"top": 1.0, "left": 0, "bottom": -0.3333333333333333, "right": 0.4166666666666667}}, {"advance": 0.4166666666666667, "unicode": 116, "atlasBounds": {"top": 16, "left": 342, "bottom": 0, "right": 346}, "planeBounds": {"top": 1.0, "left": 0, "bottom": -0.3333333333333333, "right": 0.3333333333333333}}, {"advance": 0.5833333333333334, "unicode": 117, "atlasBounds": {"top": 16, "left": 347, "bottom": 0, "right": 353}, "planeBounds": {"top": 1.0, "left": 0, "bottom": -0.3333333333333333, "right": 0.5}}, {"advance": 0.5833333333333334, "unicode": 118, "atlasBounds": {"top": 16, "left": 354, "bottom": 0, "right": 360}, "planeBounds": {"top": 1.0, "left": 0, "bottom": -0.3333333333333333, "right": 0.5}}, {"advance": 0.9166666666666666, "unicode": 119, "atlasBounds": {"top": 16, "left": 361, "bottom": 0, "right": 371}, "planeBounds": {"top": 1.0, "left": 0, "bottom": -0.3333333333333333, "right": 0.8333333333333334}}, {"advance": 0.5833333333333334, "unicode": 120, "atlasBounds": {"top": 16, "left": 372, "bottom": 0, "right": 378}, "planeBounds": {"top": 1.0, "left": 0, "bottom": -0.3333333333333333, "right": 0.5}}, {"advance": 0.5833333333333334, "unicode": 121, "atlasBounds": {"top": 16, "left": 379, "bottom": 0, "right": 385}, "planeBounds": {"top": 1.0, "left": 0, "bottom": -0.3333333333333333, "right": 0.5}}, {"advance": 0.5833333333333334, "unicode": 122, "atlasBounds": {"top": 16, "left": 386, "bottom": 0, "right": 392}, "planeBounds": {"top": 1.0, "left": 0, "bottom": -0.3333333333333333, "right": 0.5}}, {"advance": 0.5833333333333334, "unicode": 48, "atlasBounds": {"top": 16, "left": 393, "bottom": 0, "right": 399}, "planeBounds": {"top": 1.0, "left": 0, "bottom": -0.3333333333333333, "right": 0.5}}, {"advance": 0.5833333333333334, "unicode": 49, "atlasBounds": {"top": 16, "left": 400, "bottom": 0, "right": 406}, "planeBounds": {"top": 1.0, "left": 0, "bottom": -0.3333333333333333, "right": 0.5}}, {"advance": 0.5833333333333334, "unicode": 50, "atlasBounds": {"top": 16, "left": 407, "bottom": 0, "right": 413}, "planeBounds": {"top": 1.0, "left": 0, "bottom": -0.3333333333333333, "right": 0.5}}, {"advance": 0.5833333333333334, "unicode": 51, "atlasBounds": {"top": 16, "left": 414, "bottom": 0, "right": 420}, "planeBounds": {"top": 1.0, "left": 0, "bottom": -0.3333333333333333, "right": 0.5}}, {"advance": 0.5833333333333334, "unicode": 52, "atlasBounds": {"top": 16, "left": 421, "bottom": 0, "right": 427}, "planeBounds": {"top": 1.0, "left": 0, "bottom": -0.3333333333333333, "right": 0.5}}, {"advance": 0.5833333333333334, "unicode": 53, "atlasBounds": {"top": 16, "left": 428, "bottom": 0, "right": 434}, "planeBounds": {"top": 1.0, "left": 0, "bottom": -0.3333333333333333, "right": 0.5}}, {"advance": 0.5833333333333334, "unicode": 54, "atlasBounds": {"top": 16, "left": 435, "bottom": 0, "right": 441}, "planeBounds": {"top": 1.0, "left": 0, "bottom": -0.3333333333333333, "right": 0.5}}, {"advance": 0.5833333333333334, "unicode": 55, "atlasBounds": {"top": 16, "left": 442, "bottom": 0, "right": 448}, "planeBounds": {"top": 1.0, "left": 0, "bottom": -0.3333333333333333, "right": 0.5}}, {"advance": 0.5833333333333334, "unicode": 56, "atlasBounds": {"top": 16, "left": 449, "bottom": 0, "right": 455}, "planeBounds": {"top": 1.0, "left": 0, "bottom": -0.3333333333333333, "right": 0.5}}, {"advance": 0.5833333333333334, "unicode": 57, "atlasBounds": {"top": 16, "left": 456, "bottom": 0, "right": 462}, "planeBounds": {"top": 1.0, "left": 0, "bottom": -0.3333333333333333, "right": 0.5}}, {"advance": 0.25, "unicode": 46, "atlasBounds": {"top": 16, "left": 463, "bottom": 0, "right": 465}, "planeBounds": {"top": 1.0, "left": 0, "bottom": -0.3333333333333333, "right": 0.16666666666666666}}, {"advance": 0.3333333333333333, "unicode": 44, "atlasBounds": {"top": 16, "left": 466, "bottom": 0, "right": 469}, "planeBounds": {"top": 1.0, "left": 0, "bottom": -0.3333333333333333, "right": 0.25}}, {"advance": 0.3333333333333333, "unicode": 59, "atlasBounds": {"top": 16, "left": 470, "bottom": 0, "right": 473}, "planeBounds": {"top": 1.0, "left": 0, "bottom": -0.3333333333333333, "right": 0.25}}, {"advance": 0.25, "unicode": 58, "atlasBounds": {"top": 16, "left": 474, "bottom": 0, "right": 476}, "planeBounds": {"top": 1.0, "left": 0, "bottom": -0.3333333333333333, "right": 0.16666666666666666}}, {"advance": 0.4166666666666667, "unicode": 63, "atlasBounds": {"top": 16, "left": 477, "bottom": 0, "right": 481}, "planeBounds": {"top": 1.0, "left": 0, "bottom": -0.3333333333333333, "right": 0.3333333333333333}}, {"advance": 0.25, "unicode": 33, "atlasBounds": {"top": 16, "left": 482, "bottom": 0, "right": 484}, "planeBounds": {"top": 1.0, "left": 0, "bottom": -0.3333333333333333, "right": 0.16666666666666666}}, {"advance": 0.5833333333333334, "unicode": 45, "atlasBounds": {"top": 16, "left": 485, "bottom": 0, "right": 491}, "planeBounds": {"top": 1.0, "left": 0, "bottom": -0.3333333333333333, "right": 0.5}}, {"advance": 0.5833333333333334, "unicode": 95, "atlasBounds": {"top": 16, "left": 492, "bottom": 0, "right": 498}, "planeBounds": {"top": 1.0, "left": 0, "bottom": -0.3333333333333333, "right": 0.5}}, {"advance": 0.6666666666666666, "unicode": 126, "atlasBounds": {"top": 16, "left": 499, "bottom": 0, "right": 506}, "planeBounds": {"top": 1.0, "left": 0, "bottom": -0.3333333333333333, "right": 0.5833333333333334}}, {"advance": 0.6666666666666666, "unicode": 35, "atlasBounds": {"top": 16, "left": 507, "bottom": 0, "right": 514}, "planeBounds": {"top": 1.0, "left": 0, "bottom": -0.3333333333333333, "right": 0.5833333333333334}}, {"advance": 0.5, "unicode": 34, "atlasBounds": {"top": 16, "left": 515, "bottom": 0, "right": 520}, "planeBounds": {"top": 1.0, "left": 0, "bottom": -0.3333333333333333, "right": 0.4166666666666667}}, {"advance": 0.3333333333333333, "unicode": 39, "atlasBounds": {"top": 16, "left": 521, "bottom": 0, "right": 524}, "planeBounds": {"top": 1.0, "left": 0, "bottom": -0.3333333333333333, "right": 0.25}}, {"advance": 0.5833333333333334, "unicode": 38, "atlasBounds": {"top": 16, "left": 525, "bottom": 0, "right": 531}, "planeBounds": {"top": 1.0, "left": 0, "bottom": -0.3333333333333333, "right": 0.5}}, {"advance": 0.4166666666666667, "unicode": 40, "atlasBounds": {"top": 16, "left": 532, "bottom": 0, "right": 536}, "planeBounds": {"top": 1.0, "left": 0, "bottom": -0.3333333333333333, "right": 0.3333333333333333}}, {"advance": 0.4166666666666667, "unicode": 41, "atlasBounds": {"top": 16, "left": 537, "bottom": 0, "right": 541}, "planeBounds": {"top": 1.0, "left": 0, "bottom": -0.3333333333333333, "right": 0.3333333333333333}}, {"advance": 0.4166666666666667, "unicode": 91, "atlasBounds": {"top": 16, "left": 542, "bottom": 0, "right": 546}, "planeBounds": {"top": 1.0, "left": 0, "bottom": -0.3333333333333333, "right": 0.3333333333333333}}, {"advance": 0.4166666666666667, "unicode": 93, "atlasBounds": {"top": 16, "left": 547, "bottom": 0, "right": 551}, "planeBounds": {"top": 1.0, "left": 0, "bottom": -0.3333333333333333, "right": 0.3333333333333333}}, {"advance": 0.4166666666666667, "unicode": 123, "atlasBounds": {"top": 16, "left": 552, "bottom": 0, "right": 556}, "planeBounds": {"top": 1.0, "left": 0, "bottom": -0.3333333333333333, "right": 0.3333333333333333}}, {"advance": 0.4166666666666667, "unicode": 125, "atlasBounds": {"top": 16, "left": 557, "bottom": 0, "right": 561}, "planeBounds": {"top": 1.0, "left": 0, "bottom": -0.3333333333333333, "right": 0.3333333333333333}}, {"advance": 0.5, "unicode": 94, "atlasBounds": {"top": 16, "left": 562, "bottom": 0, "right": 567}, "planeBounds": {"top": 1.0, "left": 0, "bottom": -0.3333333333333333, "right": 0.4166666666666667}}, {"advance": 0.25, "unicode": 124, "atlasBounds": {"top": 16, "left": 568, "bottom": 0, "right": 570}, "planeBounds": {"top": 1.0, "left": 0, "bottom": -0.3333333333333333, "right": 0.16666666666666666}}, {"advance": 0.3333333333333333, "unicode": 96, "atlasBounds": {"top": 16, "left": 571, "bottom": 0, "right": 574}, "planeBounds": {"top": 1.0, "left": 0, "bottom": -0.3333333333333333, "right": 0.25}}, {"advance": 0.4166666666666667, "unicode": 47, "atlasBounds": {"top": 16, "left": 575, "bottom": 0, "right": 579}, "planeBounds": {"top": 1.0, "left": 0, "bottom": -0.3333333333333333, "right": 0.3333333333333333}}, {"advance": 0.4166666666666667, "unicode": 92, "atlasBounds": {"top": 16, "left": 580, "bottom": 0, "right": 584}, "planeBounds": {"top": 1.0, "left": 0, "bottom": -0.3333333333333333, "right": 0.3333333333333333}}, {"advance": 1.0, "unicode": 64, "atlasBounds": {"top": 16, "left": 585, "bottom": 0, "right": 596}, "planeBounds": {"top": 1.0, "left": 0, "bottom": -0.3333333333333333, "right": 0.9166666666666666}}, {"advance": 0.5, "unicode": 176, "atlasBounds": {"top": 16, "left": 597, "bottom": 0, "right": 602}, "planeBounds": {"top": 1.0, "left": 0, "bottom": -0.3333333333333333, "right": 0.4166666666666667}}, {"advance": 0.5833333333333334, "unicode": 43, "atlasBounds": {"top": 16, "left": 603, "bottom": 0, "right": 609}, "planeBounds": {"top": 1.0, "left": 0, "bottom": -0.3333333333333333, "right": 0.5}}, {"advance": 0.5833333333333334, "unicode": 61, "atlasBounds": {"top": 16, "left": 610, "bottom": 0, "right": 616}, "planeBounds": {"top": 1.0, "left": 0, "bottom": -0.3333333333333333, "right": 0.5}}, {"advance": 0.5833333333333334, "unicode": 42, "atlasBounds": {"top": 16, "left": 617, "bottom": 0, "right": 623}, "planeBounds": {"top": 1.0, "left": 0, "bottom": -0.3333333333333333, "right": 0.5}}, {"advance": 0.5, "unicode": 37, "atlasBounds": {"top": 16, "left": 624, "bottom": 0, "right": 629}, "planeBounds": {"top": 1.0, "left": 0, "bottom": -0.3333333333333333, "right": 0.4166666666666667}}, {"advance": 0.6666666666666666, "unicode": 8364, "atlasBounds": {"top": 16, "left": 630, "bottom": 0, "right": 637}, "planeBounds": {"top": 1.0, "left": 0, "bottom": -0.3333333333333333, "right": 0.5833333333333334}}, {"advance": 0.6666666666666666, "unicode": 36, "atlasBounds": {"top": 16, "left": 638, "bottom": 0, "right": 645}, "planeBounds": {"top": 1.0, "left": 0, "bottom": -0.3333333333333333, "right": 0.5833333333333334}}, {"advance": 0.6666666666666666, "unicode": 163, "atlasBounds": {"top": 16, "left": 646, "bottom": 0, "right": 653}, "planeBounds": {"top": 1.0, "left": 0, "bottom": -0.3333333333333333, "right": 0.5833333333333334}}, {"advance": 0.5833333333333334, "unicode": 162, "atlasBounds": {"top": 16, "left": 654, "bottom": 0, "right": 660}, "planeBounds": {"top": 1.0, "left": 0, "bottom": -0.3333333333333333, "right": 0.5}}, {"advance": 0.4166666666666667, "unicode": 60, "atlasBounds": {"top": 16, "left": 661, "bottom": 0, "right": 665}, "planeBounds": {"top": 1.0, "left": 0, "bottom": -0.3333333333333333, "right": 0.3333333333333333}}, {"advance": 0.4166666666666667, "unicode": 62, "atlasBounds": {"top": 16, "left": 666, "bottom": 0, "right": 670}, "planeBounds": {"top": 1.0, "left": 0, "bottom": -0.3333333333333333, "right": 0.3333333333333333}}, {"advance": 1.0, "unicode": 169, "atlasBounds": {"top": 16, "left": 671, "bottom": 0, "right": 682}, "planeBounds": {"top": 1.0, "left": 0, "bottom": -0.3333333333333333, "right": 0.9166666666666666}}, {"advance": 1.0, "unicode": 174, "atlasBounds": {"top": 16, "left": 683, "bottom": 0, "right": 694}, "planeBounds": {"top": 1.0, "left": 0, "bottom": -0.3333333333333333, "right": 0.9166666666666666}}, {"advance": 0.75, "unicode": 192, "atlasBounds": {"top": 16, "left": 695, "bottom": 0, "right": 703}, "planeBounds": {"top": 1.0, "left": 0, "bottom": -0.3333333333333333, "right": 0.6666666666666666}}, {"advance": 0.75, "unicode": 193, "atlasBounds": {"top": 16, "left": 704, "bottom": 0, "right": 712}, "planeBounds": {"top": 1.0, "left": 0, "bottom": -0.3333333333333333, "right": 0.6666666666666666}}, {"advance": 0.75, "unicode": 194, "atlasBounds": {"top": 16, "left": 713, "bottom": 0, "right": 721}, "planeBounds": {"top": 1.0, "left": 0, "bottom": -0.3333333333333333, "right": 0.6666666666666666}}, {"advance": 0.75, "unicode": 195, "atlasBounds": {"top": 16, "left": 722, "bottom": 0, "right": 730}, "planeBounds": {"top": 1.0, "left": 0, "bottom": -0.3333333333333333, "right": 0.6666666666666666}}, {"advance": 0.75, "unicode": 196, "atlasBounds": {"top": 16, "left": 731, "bottom": 0, "right": 739}, "planeBounds": {"top": 1.0, "left": 0, "bottom": -0.3333333333333333, "right": 0.6666666666666666}}, {"advance": 0.75, "unicode": 197, "atlasBounds": {"top": 16, "left": 740, "bottom": 0, "right": 748}, "planeBounds": {"top": 1.0, "left": 0, "bottom": -0.3333333333333333, "right": 0.6666666666666666}}, {"advance": 1.0, "unicode": 198, "atlasBounds": {"top": 16, "left": 749, "bottom": 0, "right": 760}, "planeBounds": {"top": 1.0, "left": 0, "bottom": -0.3333333333333333, "right": 0.9166666666666666}}, {"advance": 0.5833333333333334, "unicode": 199, "atlasBounds": {"top": 16, "left": 761, "bottom": 0, "right": 767}, "planeBounds": {"top": 1.0, "left": 0, "bottom": -0.3333333333333333, "right": 0.5}}, {"advance": 0.6666666666666666, "unicode": 200, "atlasBounds": {"top": 16, "left": 768, "bottom": 0, "right": 775}, "planeBounds": {"top": 1.0, "left": 0, "bottom": -0.3333333333333333, "right": 0.5833333333333334}}, {"advance": 0.6666666666666666, "unicode": 201, "atlasBounds": {"top": 16, "left": 776, "bottom": 0, "right": 783}, "planeBounds": {"top": 1.0, "left": 0, "bottom": -0.3333333333333333, "right": 0.5833333333333334}}, {"advance": 0.6666666666666666, "unicode": 202, "atlasBounds": {"top": 16, "left": 784, "bottom": 0, "right": 791}, "planeBounds": {"top": 1.0, "left": 0, "bottom": -0.3333333333333333, "right": 0.5833333333333334}}, {"advance": 0.6666666666666666, "unicode": 203, "atlasBounds": {"top": 16, "left": 792, "bottom": 0, "right": 799}, "planeBounds": {"top": 1.0, "left": 0, "bottom": -0.3333333333333333, "right": 0.5833333333333334}}, {"advance": 0.4166666666666667, "unicode": 204, "atlasBounds": {"top": 16, "left": 800, "bottom": 0, "right": 804}, "planeBounds": {"top": 1.0, "left": 0, "bottom": -0.3333333333333333, "right": 0.3333333333333333}}, {"advance": 0.4166666666666667, "unicode": 205, "atlasBounds": {"top": 16, "left": 805, "bottom": 0, "right": 809}, "planeBounds": {"top": 1.0, "left": 0, "bottom": -0.3333333333333333, "right": 0.3333333333333333}}, {"advance": 0.4166666666666667, "unicode": 206, "atlasBounds": {"top": 16, "left": 810, "bottom": 0, "right": 814}, "planeBounds": {"top": 1.0, "left": 0, "bottom": -0.3333333333333333, "right": 0.3333333333333333}}, {"advance": 0.4166666666666667, "unicode": 207, "atlasBounds": {"top": 16, "left": 815, "bottom": 0, "right": 819}, "planeBounds": {"top": 1.0, "left": 0, "bottom": -0.3333333333333333, "right": 0.3333333333333333}}, {"advance": 0.6666666666666666, "unicode": 208, "atlasBounds": {"top": 16, "left": 820, "bottom": 0, "right": 827}, "planeBounds": {"top": 1.0, "left": 0, "bottom": -0.3333333333333333, "right": 0.5833333333333334}}, {"advance": 0.8333333333333334, "unicode": 209, "atlasBounds": {"top": 16, "left": 828, "bottom": 0, "right": 837}, "planeBounds": {"top": 1.0, "left": 0, "bottom": -0.3333333333333333, "right": 0.75}}, {"advance": 0.6666666666666666, "unicode": 210, "atlasBounds": {"top": 16, "left": 838, "bottom": 0, "right": 845}, "planeBounds": {"top": 1.0, "left": 0, "bottom": -0.3333333333333333, "right": 0.5833333333333334}}, {"advance": 0.6666666666666666, "unicode": 211, "atlasBounds": {"top": 16, "left": 846, "bottom": 0, "right": 853}, "planeBounds": {"top": 1.0, "left": 0, "bottom": -0.3333333333333333, "right": 0.5833333333333334}}, {"advance": 0.6666666666666666, "unicode": 212, "atlasBounds": {"top": 16, "left": 854, "bottom": 0, "right": 861}, "planeBounds": {"top": 1.0, "left": 0, "bottom": -0.3333333333333333, "right": 0.5833333333333334}}, {"advance": 0.6666666666666666, "unicode": 213, "atlasBounds": {"top": 16, "left": 862, "bottom": 0, "right": 869}, "planeBounds": {"top": 1.0, "left": 0, "bottom": -0.3333333333333333, "right": 0.5833333333333334}}, {"advance": 0.6666666666666666, "unicode": 214, "atlasBounds": {"top": 16, "left": 870, "bottom": 0, "right": 877}, "planeBounds": {"top": 1.0, "left": 0, "bottom": -0.3333333333333333, "right": 0.5833333333333334}}, {"advance": 0.6666666666666666, "unicode": 216, "atlasBounds": {"top": 16, "left": 878, "bottom": 0, "right": 885}, "planeBounds": {"top": 1.0, "left": 0, "bottom": -0.3333333333333333, "right": 0.5833333333333334}}, {"advance": 1.0, "unicode": 338, "atlasBounds": {"top": 16, "left": 886, "bottom": 0, "right": 897}, "planeBounds": {"top": 1.0, "left": 0, "bottom": -0.3333333333333333, "right": 0.9166666666666666}}, {"advance": 0.6666666666666666, "unicode": 217, "atlasBounds": {"top": 16, "left": 898, "bottom": 0, "right": 905}, "planeBounds": {"top": 1.0, "left": 0, "bottom": -0.3333333333333333, "right": 0.5833333333333334}}, {"advance": 0.6666666666666666, "unicode": 218, "atlasBounds": {"top": 16, "left": 906, "bottom": 0, "right": 913}, "planeBounds": {"top": 1.0, "left": 0, "bottom": -0.3333333333333333, "right": 0.5833333333333334}}, {"advance": 0.6666666666666666, "unicode": 219, "atlasBounds": {"top": 16, "left": 914, "bottom": 0, "right": 921}, "planeBounds": {"top": 1.0, "left": 0, "bottom": -0.3333333333333333, "right": 0.5833333333333334}}, {"advance": 0.6666666666666666, "unicode": 220, "atlasBounds": {"top": 16, "left": 922, "bottom": 0, "right": 929}, "planeBounds": {"top": 1.0, "left": 0, "bottom": -0.3333333333333333, "right": 0.5833333333333334}}, {"advance": 0.75, "unicode": 221, "atlasBounds": {"top": 16, "left": 930, "bottom": 0, "right": 938}, "planeBounds": {"top": 1.0, "left": 0, "bottom": -0.3333333333333333, "right": 0.6666666666666666}}, {"advance": 0.5833333333333334, "unicode": 222, "atlasBounds": {"top": 16, "left": 939, "bottom": 0, "right": 945}, "planeBounds": {"top": 1.0, "left": 0, "bottom": -0.3333333333333333, "right": 0.5}}, {"advance": 0.5833333333333334, "unicode": 224, "atlasBounds": {"top": 16, "left": 946, "bottom": 0, "right": 952}, "planeBounds": {"top": 1.0, "left": 0, "bottom": -0.3333333333333333, "right": 0.5}}, {"advance": 0.5833333333333334, "unicode": 225, "atlasBounds": {"top": 16, "left": 953, "bottom": 0, "right": 959}, "planeBounds": {"top": 1.0, "left": 0, "bottom": -0.3333333333333333, "right": 0.5}}, {"advance": 0.5833333333333334, "unicode": 226, "atlasBounds": {"top": 16, "left": 960, "bottom": 0, "right": 966}, "planeBounds": {"top": 1.0, "left": 0, "bottom": -0.3333333333333333, "right": 0.5}}, {"advance": 0.5833333333333334, "unicode": 227, "atlasBounds": {"top": 16, "left": 967, "bottom": 0, "right": 973}, "planeBounds": {"top": 1.0, "left": 0, "bottom": -0.3333333333333333, "right": 0.5}}, {"advance": 0.5833333333333334, "unicode": 228, "atlasBounds": {"top": 16, "left": 974, "bottom": 0, "right": 980}, "planeBounds": {"top": 1.0, "left": 0, "bottom": -0.3333333333333333, "right": 0.5}}, {"advance": 0.5833333333333334, "unicode": 229, "atlasBounds": {"top": 16, "left": 981, "bottom": 0, "right": 987}, "planeBounds": {"top": 1.0, "left": 0, "bottom": -0.3333333333333333, "right": 0.5}}, {"advance": 0.9166666666666666, "unicode": 230, "atlasBounds": {"top": 16, "left": 988, "bottom": 0, "right": 998}, "planeBounds": {"top": 1.0, "left": 0, "bottom": -0.3333333333333333, "right": 0.8333333333333334}}, {"advance": 0.5833333333333334, "unicode": 231, "atlasBounds": {"top": 16, "left": 999, "bottom": 0, "right": 1005}, "planeBounds": {"top": 1.0, "left": 0, "bottom": -0.3333333333333333, "right": 0.5}}, {"advance": 0.5833333333333334, "unicode": 232, "atlasBounds": {"top": 16, "left": 1006, "bottom": 0, "right": 1012}, "planeBounds": {"top": 1.0, "left": 0, "bottom": -0.3333333333333333, "right": 0.5}}, {"advance": 0.5833333333333334, "unicode": 233, "atlasBounds": {"top": 16, "left": 1013, "bottom": 0, "right": 1019}, "planeBounds": {"top": 1.0, "left": 0, "bottom": -0.3333333333333333, "right": 0.5}}, {"advance": 0.5833333333333334, "unicode": 234, "atlasBounds": {"top": 16, "left": 1020, "bottom": 0, "right": 1026}, "planeBounds": {"top": 1.0, "left": 0, "bottom": -0.3333333333333333, "right": 0.5}}, {"advance": 0.5833333333333334, "unicode": 235, "atlasBounds": {"top": 16, "left": 1027, "bottom": 0, "right": 1033}, "planeBounds": {"top": 1.0, "left": 0, "bottom": -0.3333333333333333, "right": 0.5}}, {"advance": 0.4166666666666667, "unicode": 236, "atlasBounds": {"top": 16, "left": 1034, "bottom": 0, "right": 1038}, "planeBounds": {"top": 1.0, "left": 0, "bottom": -0.3333333333333333, "right": 0.3333333333333333}}, {"advance": 0.4166666666666667, "unicode": 237, "atlasBounds": {"top": 16, "left": 1039, "bottom": 0, "right": 1043}, "planeBounds": {"top": 1.0, "left": 0, "bottom": -0.3333333333333333, "right": 0.3333333333333333}}, {"advance": 0.4166666666666667, "unicode": 238, "atlasBounds": {"top": 16, "left": 1044, "bottom": 0, "right": 1048}, "planeBounds": {"top": 1.0, "left": 0, "bottom": -0.3333333333333333, "right": 0.3333333333333333}}, {"advance": 0.4166666666666667, "unicode": 239, "atlasBounds": {"top": 16, "left": 1049, "bottom": 0, "right": 1053}, "planeBounds": {"top": 1.0, "left": 0, "bottom": -0.3333333333333333, "right": 0.3333333333333333}}, {"advance": 0.5833333333333334, "unicode": 240, "atlasBounds": {"top": 16, "left": 1054, "bottom": 0, "right": 1060}, "planeBounds": {"top": 1.0, "left": 0, "bottom": -0.3333333333333333, "right": 0.5}}, {"advance": 0.5833333333333334, "unicode": 241, "atlasBounds": {"top": 16, "left": 1061, "bottom": 0, "right": 1067}, "planeBounds": {"top": 1.0, "left": 0, "bottom": -0.3333333333333333, "right": 0.5}}, {"advance": 0.5833333333333334, "unicode": 242, "atlasBounds": {"top": 16, "left": 1068, "bottom": 0, "right": 1074}, "planeBounds": {"top": 1.0, "left": 0, "bottom": -0.3333333333333333, "right": 0.5}}, {"advance": 0.5833333333333334, "unicode": 243, "atlasBounds": {"top": 16, "left": 1075, "bottom": 0, "right": 1081}, "planeBounds": {"top": 1.0, "left": 0, "bottom": -0.3333333333333333, "right": 0.5}}, {"advance": 0.5833333333333334, "unicode": 244, "atlasBounds": {"top": 16, "left": 1082, "bottom": 0, "right": 1088}, "planeBounds": {"top": 1.0, "left": 0, "bottom": -0.3333333333333333, "right": 0.5}}, {"advance": 0.5833333333333334, "unicode": 245, "atlasBounds": {"top": 16, "left": 1089, "bottom": 0, "right": 1095}, "planeBounds": {"top": 1.0, "left": 0, "bottom": -0.3333333333333333, "right": 0.5}}, {"advance": 0.5833333333333334, "unicode": 246, "atlasBounds": {"top": 16, "left": 1096, "bottom": 0, "right": 1102}, "planeBounds": {"top": 1.0, "left": 0, "bottom": -0.3333333333333333, "right": 0.5}}, {"advance": 0.5833333333333334, "unicode": 248, "atlasBounds": {"top": 16, "left": 1103, "bottom": 0, "right": 1109}, "planeBounds": {"top": 1.0, "left": 0, "bottom": -0.3333333333333333, "right": 0.5}}, {"advance": 0.9166666666666666, "unicode": 339, "atlasBounds": {"top": 16, "left": 1110, "bottom": 0, "right": 1120}, "planeBounds": {"top": 1.0, "left": 0, "bottom": -0.3333333333333333, "right": 0.8333333333333334}}, {"advance": 0.5833333333333334, "unicode": 249, "atlasBounds": {"top": 16, "left": 1121, "bottom": 0, "right": 1127}, "planeBounds": {"top": 1.0, "left": 0, "bottom": -0.3333333333333333, "right": 0.5}}, {"advance": 0.5833333333333334, "unicode": 250, "atlasBounds": {"top": 16, "left": 1128, "bottom": 0, "right": 1134}, "planeBounds": {"top": 1.0, "left": 0, "bottom": -0.3333333333333333, "right": 0.5}}, {"advance": 0.5833333333333334, "unicode": 251, "atlasBounds": {"top": 16, "left": 1135, "bottom": 0, "right": 1141}, "planeBounds": {"top": 1.0, "left": 0, "bottom": -0.3333333333333333, "right": 0.5}}, {"advance": 0.5833333333333334, "unicode": 252, "atlasBounds": {"top": 16, "left": 1142, "bottom": 0, "right": 1148}, "planeBounds": {"top": 1.0, "left": 0, "bottom": -0.3333333333333333, "right": 0.5}}, {"advance": 0.5833333333333334, "unicode": 253, "atlasBounds": {"top": 16, "left": 1149, "bottom": 0, "right": 1155}, "planeBounds": {"top": 1.0, "left": 0, "bottom": -0.3333333333333333, "right": 0.5}}, {"advance": 0.5833333333333334, "unicode": 254, "atlasBounds": {"top": 16, "left": 1156, "bottom": 0, "right": 1162}, "planeBounds": {"top": 1.0, "left": 0, "bottom": -0.3333333333333333, "right": 0.5}}, {"advance": 0.6666666666666666, "unicode": 223, "atlasBounds": {"top": 16, "left": 1163, "bottom": 0, "right": 1170}, "planeBounds": {"top": 1.0, "left": 0, "bottom": -0.3333333333333333, "right": 0.5833333333333334}}, {"advance": 0.5833333333333334, "unicode": 255, "atlasBounds": {"top": 16, "left": 1171, "bottom": 0, "right": 1177}, "planeBounds": {"top": 1.0, "left": 0, "bottom": -0.3333333333333333, "right": 0.5}}, {"advance": 0.4166666666666667, "unicode": 191, "atlasBounds": {"top": 16, "left": 1178, "bottom": 0, "right": 1182}, "planeBounds": {"top": 1.0, "left": 0, "bottom": -0.3333333333333333, "right": 0.3333333333333333}}, {"advance": 0.25, "unicode": 161, "atlasBounds": {"top": 16, "left": 1183, "bottom": 0, "right": 1185}, "planeBounds": {"top": 1.0, "left": 0, "bottom": -0.3333333333333333, "right": 0.16666666666666666}}], "kerning": [], "metrics": {"ascender": 0.75, "descender": -0.3333333333333333, "lineHeight": 1.3333333333333333, "underlineThickness": 0.08333333333333333, "underlineY": -0.08333333333333333}}